sentimentAnalisis/__init__.py
sentimentAnalisis/main.py
sentiment_analysis/__init__.py
sentiment_analysis/main.py
sentimentAnalisis1.1-0.1.1.dist-info/LICENSE
sentimentAnalisis1.1-0.1.1.dist-info/METADATA
sentimentAnalisis1.1-0.1.1.dist-info/WHEEL
sentimentAnalisis1.1-0.1.1.dist-info/top_level.txt
sentimentAnalisis1.1-0.1.1.dist-info/RECORD
